{
  "$schema": "https://developer.microsoft.com/json-schemas/fabric/item/report/definition/visualContainer/2.4.0/schema.json",
  "name": "04c2904c8db6191580d2",
  "position": {
    "x": 23.333333333333336,
    "y": 1840,
    "z": 74000,
    "height": 41.666666666666671,
    "width": 381.66666666666669,
    "tabOrder": 74000
  },
  "visual": {
    "visualType": "textbox",
    "objects": {
      "general": [
        {
          "properties": {
            "paragraphs": [
              {
                "textRuns": [
                  {
                    "value": "Note: AI Model scores may change depending on filtering.",
                    "textStyle": {
                      "fontSize": "9pt",
                      "color": "#e6e6e6"
                    }
                  }
                ]
              }
            ]
          }
        }
      ]
    },
    "visualContainerObjects": {
      "background": [
        {
          "properties": {
            "show": {
              "expr": {
                "Literal": {
                  "Value": "false"
                }
              }
            }
          }
        }
      ]
    },
    "drillFilterOtherVisuals": true
  }
}