{
  "$schema": "https://developer.microsoft.com/json-schemas/fabric/item/report/definition/visualContainer/2.4.0/schema.json",
  "name": "360407c03430527c42a1",
  "position": {
    "x": 63.999938964843743,
    "y": 108.33333333333334,
    "z": 11000,
    "height": 608.33333333333337,
    "width": 491.66666666666669,
    "tabOrder": 11000
  },
  "visual": {
    "visualType": "tableEx",
    "query": {
      "queryState": {
        "Values": {
          "projections": [
            {
              "field": {
                "Column": {
                  "Expression": {
                    "SourceRef": {
                      "Entity": "metadata_performance_metrics"
                    }
                  },
                  "Property": "metric_name"
                }
              },
              "queryRef": "metadata_performance_metrics.metric_name",
              "nativeQueryRef": "metric_name"
            },
            {
              "field": {
                "Measure": {
                  "Expression": {
                    "SourceRef": {
                      "Entity": "performance_metric_1"
                    }
                  },
                  "Property": "meas.performance_metric_value"
                }
              },
              "queryRef": "performance_metric_1.meas.performance_metric_value",
              "nativeQueryRef": "meas.performance_metric_value"
            },
            {
              "field": {
                "Column": {
                  "Expression": {
                    "SourceRef": {
                      "Entity": "metadata_performance_metrics"
                    }
                  },
                  "Property": "metric_prefix"
                }
              },
              "queryRef": "metadata_performance_metrics.metric_prefix",
              "nativeQueryRef": "metric_prefix"
            },
            {
              "field": {
                "Column": {
                  "Expression": {
                    "SourceRef": {
                      "Entity": "metadata_performance_metrics"
                    }
                  },
                  "Property": "metric_format"
                }
              },
              "queryRef": "metadata_performance_metrics.metric_format",
              "nativeQueryRef": "metric_format"
            },
            {
              "field": {
                "Column": {
                  "Expression": {
                    "SourceRef": {
                      "Entity": "metadata_performance_metrics"
                    }
                  },
                  "Property": "metric_prio"
                }
              },
              "queryRef": "metadata_performance_metrics.metric_prio",
              "nativeQueryRef": "metric_prio"
            }
          ]
        }
      },
      "sortDefinition": {
        "sort": [
          {
            "field": {
              "Column": {
                "Expression": {
                  "SourceRef": {
                    "Entity": "metadata_performance_metrics"
                  }
                },
                "Property": "metric_name"
              }
            },
            "direction": "Ascending"
          }
        ]
      }
    },
    "objects": {
      "columnWidth": [
        {
          "properties": {
            "value": {
              "expr": {
                "Literal": {
                  "Value": "215.33333329426833D"
                }
              }
            }
          },
          "selector": {
            "metadata": "metadata_performance_metrics.metric_name"
          }
        },
        {
          "properties": {
            "value": {
              "expr": {
                "Literal": {
                  "Value": "100.66666792332292D"
                }
              }
            }
          },
          "selector": {
            "metadata": "performance_metric_1.meas.performance_metric_value"
          }
        }
      ]
    },
    "drillFilterOtherVisuals": true
  },
  "filterConfig": {
    "filters": [
      {
        "name": "e90d7a79e70e2e91d814",
        "field": {
          "Column": {
            "Expression": {
              "SourceRef": {
                "Entity": "performance_metric_format"
              }
            },
            "Property": "Name"
          }
        },
        "type": "Categorical",
        "howCreated": "User"
      },
      {
        "name": "e18bf44133309940ad68",
        "field": {
          "Column": {
            "Expression": {
              "SourceRef": {
                "Entity": "metadata_performance_metrics"
              }
            },
            "Property": "metric_name"
          }
        },
        "type": "Categorical"
      },
      {
        "name": "269f27f4bb6294bc91e4",
        "field": {
          "Measure": {
            "Expression": {
              "SourceRef": {
                "Entity": "performance_metric_1"
              }
            },
            "Property": "meas.performance_metric_value"
          }
        },
        "type": "Advanced"
      },
      {
        "name": "fcdeec64ea1cb21f11fc",
        "field": {
          "Column": {
            "Expression": {
              "SourceRef": {
                "Entity": "metadata_performance_metrics"
              }
            },
            "Property": "metric_prefix"
          }
        },
        "type": "Categorical"
      },
      {
        "name": "4bb231ea85a0e200b740",
        "field": {
          "Column": {
            "Expression": {
              "SourceRef": {
                "Entity": "metadata_performance_metrics"
              }
            },
            "Property": "metric_format"
          }
        },
        "type": "Categorical"
      },
      {
        "name": "9fe0e88e358b030e1f8f",
        "field": {
          "Column": {
            "Expression": {
              "SourceRef": {
                "Entity": "metadata_performance_metrics"
              }
            },
            "Property": "metric_prio"
          }
        },
        "type": "Categorical"
      }
    ]
  }
}