{
  "$schema": "https://developer.microsoft.com/json-schemas/fabric/item/report/definition/visualContainer/2.4.0/schema.json",
  "name": "8225ab04bcaec7cfe445",
  "position": {
    "x": 1167.7134895327326,
    "y": 386.36615157305732,
    "z": 49000,
    "height": 51.865112823969447,
    "width": 89.406742314923775,
    "tabOrder": 59000
  },
  "visual": {
    "visualType": "card",
    "query": {
      "queryState": {
        "Values": {
          "projections": [
            {
              "field": {
                "Measure": {
                  "Expression": {
                    "SourceRef": {
                      "Entity": "ssr_history"
                    }
                  },
                  "Property": "meas.ssr_history_generated_pipeline_amt_diff"
                }
              },
              "queryRef": "ssr_history.meas.ssr_history_generated_pipeline_amt_diff",
              "nativeQueryRef": "meas.ssr_history_generated_pipeline_amt_diff"
            }
          ]
        }
      },
      "sortDefinition": {
        "sort": [
          {
            "field": {
              "Measure": {
                "Expression": {
                  "SourceRef": {
                    "Entity": "ssr_history"
                  }
                },
                "Property": "meas.ssr_history_generated_pipeline_amt_diff"
              }
            },
            "direction": "Descending"
          }
        ],
        "isDefaultSort": true
      }
    },
    "objects": {
      "labels": [
        {
          "properties": {
            "fontSize": {
              "expr": {
                "Literal": {
                  "Value": "13D"
                }
              }
            },
            "color": {
              "solid": {
                "color": {
                  "expr": {
                    "Conditional": {
                      "Cases": [
                        {
                          "Condition": {
                            "And": {
                              "Left": {
                                "Comparison": {
                                  "ComparisonKind": 1,
                                  "Left": {
                                    "Measure": {
                                      "Expression": {
                                        "SourceRef": {
                                          "Entity": "ssr_history"
                                        }
                                      },
                                      "Property": "meas.ssr_history_mgmt_rpt_pipeline_amt_ytd_sply_diff"
                                    }
                                  },
                                  "Right": {
                                    "Literal": {
                                      "Value": "0D"
                                    }
                                  }
                                }
                              },
                              "Right": {
                                "Comparison": {
                                  "ComparisonKind": 4,
                                  "Left": {
                                    "Measure": {
                                      "Expression": {
                                        "SourceRef": {
                                          "Entity": "ssr_history"
                                        }
                                      },
                                      "Property": "meas.ssr_history_mgmt_rpt_pipeline_amt_ytd_sply_diff"
                                    }
                                  },
                                  "Right": {
                                    "Literal": {
                                      "Value": "5000D"
                                    }
                                  }
                                }
                              }
                            }
                          },
                          "Value": {
                            "Literal": {
                              "Value": "'#658D00'"
                            }
                          }
                        },
                        {
                          "Condition": {
                            "Comparison": {
                              "ComparisonKind": 0,
                              "Left": {
                                "Measure": {
                                  "Expression": {
                                    "SourceRef": {
                                      "Entity": "ssr_history"
                                    }
                                  },
                                  "Property": "meas.ssr_history_mgmt_rpt_pipeline_amt_ytd_sply_diff"
                                }
                              },
                              "Right": {
                                "Literal": {
                                  "Value": "0D"
                                }
                              }
                            }
                          },
                          "Value": {
                            "Literal": {
                              "Value": "'#808080'"
                            }
                          }
                        },
                        {
                          "Condition": {
                            "And": {
                              "Left": {
                                "Comparison": {
                                  "ComparisonKind": 2,
                                  "Left": {
                                    "Measure": {
                                      "Expression": {
                                        "SourceRef": {
                                          "Entity": "ssr_history"
                                        }
                                      },
                                      "Property": "meas.ssr_history_mgmt_rpt_pipeline_amt_ytd_sply_diff"
                                    }
                                  },
                                  "Right": {
                                    "Literal": {
                                      "Value": "-5000D"
                                    }
                                  }
                                }
                              },
                              "Right": {
                                "Comparison": {
                                  "ComparisonKind": 3,
                                  "Left": {
                                    "Measure": {
                                      "Expression": {
                                        "SourceRef": {
                                          "Entity": "ssr_history"
                                        }
                                      },
                                      "Property": "meas.ssr_history_mgmt_rpt_pipeline_amt_ytd_sply_diff"
                                    }
                                  },
                                  "Right": {
                                    "Literal": {
                                      "Value": "0D"
                                    }
                                  }
                                }
                              }
                            }
                          },
                          "Value": {
                            "Literal": {
                              "Value": "'#941148'"
                            }
                          }
                        }
                      ]
                    }
                  }
                }
              }
            },
            "bold": {
              "expr": {
                "Literal": {
                  "Value": "true"
                }
              }
            }
          }
        }
      ],
      "categoryLabels": [
        {
          "properties": {
            "show": {
              "expr": {
                "Literal": {
                  "Value": "false"
                }
              }
            }
          }
        }
      ],
      "wordWrap": [
        {
          "properties": {
            "show": {
              "expr": {
                "Literal": {
                  "Value": "false"
                }
              }
            }
          }
        }
      ]
    },
    "visualContainerObjects": {
      "background": [
        {
          "properties": {
            "show": {
              "expr": {
                "Literal": {
                  "Value": "true"
                }
              }
            },
            "color": {
              "solid": {
                "color": {
                  "expr": {
                    "Conditional": {
                      "Cases": [
                        {
                          "Condition": {
                            "Comparison": {
                              "ComparisonKind": 1,
                              "Left": {
                                "Measure": {
                                  "Expression": {
                                    "SourceRef": {
                                      "Entity": "ssr_history"
                                    }
                                  },
                                  "Property": "meas.ssr_history_generated_pipeline_amt_diff"
                                }
                              },
                              "Right": {
                                "Literal": {
                                  "Value": "0D"
                                }
                              }
                            }
                          },
                          "Value": {
                            "Literal": {
                              "Value": "'#D8F792'"
                            }
                          }
                        },
                        {
                          "Condition": {
                            "Comparison": {
                              "ComparisonKind": 0,
                              "Left": {
                                "Measure": {
                                  "Expression": {
                                    "SourceRef": {
                                      "Entity": "ssr_history"
                                    }
                                  },
                                  "Property": "meas.ssr_history_generated_pipeline_amt_diff"
                                }
                              },
                              "Right": {
                                "Literal": {
                                  "Value": "0D"
                                }
                              }
                            }
                          },
                          "Value": {
                            "Literal": {
                              "Value": "'#E6E6E6'"
                            }
                          }
                        },
                        {
                          "Condition": {
                            "Comparison": {
                              "ComparisonKind": 3,
                              "Left": {
                                "Measure": {
                                  "Expression": {
                                    "SourceRef": {
                                      "Entity": "ssr_history"
                                    }
                                  },
                                  "Property": "meas.ssr_history_generated_pipeline_amt_diff"
                                }
                              },
                              "Right": {
                                "Literal": {
                                  "Value": "0D"
                                }
                              }
                            }
                          },
                          "Value": {
                            "Literal": {
                              "Value": "'#DD648C'"
                            }
                          }
                        }
                      ]
                    }
                  }
                }
              }
            }
          }
        }
      ],
      "border": [
        {
          "properties": {
            "show": {
              "expr": {
                "Literal": {
                  "Value": "true"
                }
              }
            },
            "color": {
              "solid": {
                "color": {
                  "expr": {
                    "ThemeDataColor": {
                      "ColorId": 2,
                      "Percent": 0.4
                    }
                  }
                }
              }
            },
            "radius": {
              "expr": {
                "Literal": {
                  "Value": "16D"
                }
              }
            }
          }
        }
      ]
    },
    "drillFilterOtherVisuals": true
  },
  "filterConfig": {
    "filters": [
      {
        "name": "b993b5c9b5382d805508",
        "field": {
          "Column": {
            "Expression": {
              "SourceRef": {
                "Entity": "time_intelligence"
              }
            },
            "Property": "filt_item"
          }
        },
        "type": "Categorical",
        "filter": {
          "Version": 2,
          "From": [
            {
              "Name": "t",
              "Entity": "time_intelligence",
              "Type": 0
            }
          ],
          "Where": [
            {
              "Condition": {
                "In": {
                  "Expressions": [
                    {
                      "Column": {
                        "Expression": {
                          "SourceRef": {
                            "Source": "t"
                          }
                        },
                        "Property": "filt_item"
                      }
                    }
                  ],
                  "Values": [
                    [
                      {
                        "Literal": {
                          "Value": "'YTD'"
                        }
                      }
                    ]
                  ]
                }
              }
            }
          ]
        },
        "howCreated": "User"
      }
    ]
  }
}