{
  "$schema": "https://developer.microsoft.com/json-schemas/fabric/item/report/definition/visualContainer/2.5.0/schema.json",
  "name": "d588cdc223605da9a137",
  "position": {
    "x": 22.681098456914064,
    "y": 153.43096014971277,
    "z": 13000,
    "height": 42.678622711696541,
    "width": 484.3041586214373,
    "tabOrder": 7000
  },
  "visual": {
    "visualType": "textbox",
    "objects": {
      "general": [
        {
          "properties": {
            "paragraphs": [
              {
                "textRuns": [
                  {
                    "value": "How is Rep Time Allocation Calculated?",
                    "textStyle": {
                      "fontFamily": "Segoe (Bold)",
                      "fontSize": "18pt",
                      "color": "#e6e6e6"
                    }
                  }
                ]
              }
            ]
          }
        }
      ]
    },
    "visualContainerObjects": {
      "title": [
        {
          "properties": {
            "show": {
              "expr": {
                "Literal": {
                  "Value": "false"
                }
              }
            }
          }
        }
      ],
      "background": [
        {
          "properties": {
            "transparency": {
              "expr": {
                "Literal": {
                  "Value": "100D"
                }
              }
            }
          }
        }
      ]
    },
    "drillFilterOtherVisuals": true
  }
}