{
  "$schema": "https://developer.microsoft.com/json-schemas/fabric/item/report/definition/visualContainer/2.5.0/schema.json",
  "name": "5d4abb84201112016bcf",
  "position": {
    "x": 12.571428571428571,
    "y": 1140.5714285714287,
    "z": 11000,
    "height": 172.57142857142858,
    "width": 1267.4285714285713,
    "tabOrder": 10000
  },
  "visual": {
    "visualType": "tableEx",
    "query": {
      "queryState": {
        "Values": {
          "projections": [
            {
              "field": {
                "Column": {
                  "Expression": {
                    "SourceRef": {
                      "Entity": "ssr_history"
                    }
                  },
                  "Property": "step_id"
                }
              },
              "queryRef": "ssr_history.step_id",
              "displayName": "-"
            },
            {
              "field": {
                "Column": {
                  "Expression": {
                    "SourceRef": {
                      "Entity": "ssr_history"
                    }
                  },
                  "Property": "step_sequence"
                }
              },
              "queryRef": "Sum(ssr_history.step_sequence)",
              "nativeQueryRef": "step_sequence"
            },
            {
              "field": {
                "Column": {
                  "Expression": {
                    "SourceRef": {
                      "Entity": "ssr_history"
                    }
                  },
                  "Property": "step_name"
                }
              },
              "queryRef": "ssr_history.step_name"
            },
            {
              "field": {
                "Column": {
                  "Expression": {
                    "SourceRef": {
                      "Entity": "ssr_history"
                    }
                  },
                  "Property": "_sys_filt_start_date"
                }
              },
              "queryRef": "ssr_history._sys_filt_start_date"
            },
            {
              "field": {
                "Column": {
                  "Expression": {
                    "SourceRef": {
                      "Entity": "ssr_history"
                    }
                  },
                  "Property": "_sys_filt_end_date"
                }
              },
              "queryRef": "ssr_history._sys_filt_end_date"
            },
            {
              "field": {
                "Column": {
                  "Expression": {
                    "SourceRef": {
                      "Entity": "ssr_history"
                    }
                  },
                  "Property": "step_outcome"
                }
              },
              "queryRef": "ssr_history.step_outcome",
              "displayName": "step_outcome"
            },
            {
              "field": {
                "Column": {
                  "Expression": {
                    "SourceRef": {
                      "Entity": "ssr_history"
                    }
                  },
                  "Property": "entity_qual_bucket"
                }
              },
              "queryRef": "ssr_history.entity_qual_bucket"
            },
            {
              "field": {
                "Aggregation": {
                  "Expression": {
                    "Column": {
                      "Expression": {
                        "SourceRef": {
                          "Entity": "ssr_history"
                        }
                      },
                      "Property": "step_success_prob"
                    }
                  },
                  "Function": 0
                }
              },
              "queryRef": "Sum(ssr_history.step_success_prob)",
              "displayName": "step_success_prob"
            },
            {
              "field": {
                "Column": {
                  "Expression": {
                    "SourceRef": {
                      "Entity": "ssr_history"
                    }
                  },
                  "Property": "opp_booking_amt"
                }
              },
              "queryRef": "Sum(ssr_history.opp_booking_amt)",
              "nativeQueryRef": "opp_booking_amt"
            },
            {
              "field": {
                "Column": {
                  "Expression": {
                    "SourceRef": {
                      "Entity": "ssr_history"
                    }
                  },
                  "Property": "opp_final_stage"
                }
              },
              "queryRef": "ssr_history.opp_final_stage"
            },
            {
              "field": {
                "Aggregation": {
                  "Expression": {
                    "Column": {
                      "Expression": {
                        "SourceRef": {
                          "Entity": "ssr_history"
                        }
                      },
                      "Property": "step_length_in_days"
                    }
                  },
                  "Function": 0
                }
              },
              "queryRef": "Sum(ssr_history.step_length_in_days)",
              "displayName": "step_length_in_days"
            },
            {
              "field": {
                "Column": {
                  "Expression": {
                    "SourceRef": {
                      "Entity": "users"
                    }
                  },
                  "Property": "col.full_name"
                }
              },
              "queryRef": "users.col.full_name",
              "displayName": "col.full_name"
            },
            {
              "field": {
                "Column": {
                  "Expression": {
                    "SourceRef": {
                      "Entity": "ssr_history"
                    }
                  },
                  "Property": "step_owner_user_role"
                }
              },
              "queryRef": "ssr_history.step_owner_user_role",
              "displayName": "step_owner_user_role"
            },
            {
              "field": {
                "Column": {
                  "Expression": {
                    "SourceRef": {
                      "Entity": "ssr_history"
                    }
                  },
                  "Property": "step_users_tot"
                }
              },
              "queryRef": "Sum(ssr_history.step_users_tot)",
              "nativeQueryRef": "step_users_tot"
            },
            {
              "field": {
                "Column": {
                  "Expression": {
                    "SourceRef": {
                      "Entity": "ssr_history"
                    }
                  },
                  "Property": "stkhlds_all_act_count"
                }
              },
              "queryRef": "Sum(ssr_history.stkhlds_all_act_count)",
              "nativeQueryRef": "stkhlds_all_act_count"
            },
            {
              "field": {
                "Column": {
                  "Expression": {
                    "SourceRef": {
                      "Entity": "ssr_history"
                    }
                  },
                  "Property": "stkhlds_all_act_eng_count"
                }
              },
              "queryRef": "Sum(ssr_history.stkhlds_all_act_eng_count)",
              "nativeQueryRef": "stkhlds_all_act_eng_count"
            },
            {
              "field": {
                "Column": {
                  "Expression": {
                    "SourceRef": {
                      "Entity": "ssr_history"
                    }
                  },
                  "Property": "stkhlds_secondary_contact_title_seniority"
                }
              },
              "queryRef": "ssr_history.stkhlds_secondary_contact_title_seniority"
            }
          ]
        }
      },
      "sortDefinition": {
        "sort": [
          {
            "field": {
              "Column": {
                "Expression": {
                  "SourceRef": {
                    "Entity": "ssr_history"
                  }
                },
                "Property": "step_sequence"
              }
            },
            "direction": "Ascending"
          }
        ]
      }
    },
    "objects": {
      "total": [
        {
          "properties": {
            "totals": {
              "expr": {
                "Literal": {
                  "Value": "false"
                }
              }
            },
            "outlineStyle": {
              "expr": {
                "Literal": {
                  "Value": "0D"
                }
              }
            }
          }
        }
      ],
      "columnWidth": [
        {
          "properties": {
            "value": {
              "expr": {
                "Literal": {
                  "Value": "67.35894812795314D"
                }
              }
            }
          },
          "selector": {
            "metadata": "Sum(ssr_history.step_success_prob)"
          }
        },
        {
          "properties": {
            "value": {
              "expr": {
                "Literal": {
                  "Value": "69.42726042036138D"
                }
              }
            }
          },
          "selector": {
            "metadata": "ssr_history.entity_qual_bucket"
          }
        },
        {
          "properties": {
            "value": {
              "expr": {
                "Literal": {
                  "Value": "80.78583014823568D"
                }
              }
            }
          },
          "selector": {
            "metadata": "ssr_history.step_name"
          }
        },
        {
          "properties": {
            "value": {
              "expr": {
                "Literal": {
                  "Value": "72.4996024227209D"
                }
              }
            }
          },
          "selector": {
            "metadata": "Sum(ssr_history.step_length_in_days)"
          }
        },
        {
          "properties": {
            "value": {
              "expr": {
                "Literal": {
                  "Value": "78.68675970504604D"
                }
              }
            }
          },
          "selector": {
            "metadata": "ssr_history.step_owner_user_role"
          }
        },
        {
          "properties": {
            "value": {
              "expr": {
                "Literal": {
                  "Value": "68.05489333637537D"
                }
              }
            }
          },
          "selector": {
            "metadata": "ssr_history.opp_final_stage"
          }
        },
        {
          "properties": {
            "value": {
              "expr": {
                "Literal": {
                  "Value": "4D"
                }
              }
            }
          },
          "selector": {
            "metadata": "ssr_history.step_id"
          }
        },
        {
          "properties": {
            "value": {
              "expr": {
                "Literal": {
                  "Value": "72.44895789694489D"
                }
              }
            }
          },
          "selector": {
            "metadata": "ssr_history._sys_filt_start_date"
          }
        },
        {
          "properties": {
            "value": {
              "expr": {
                "Literal": {
                  "Value": "66.96280221081882D"
                }
              }
            }
          },
          "selector": {
            "metadata": "ssr_history._sys_filt_end_date"
          }
        },
        {
          "properties": {
            "value": {
              "expr": {
                "Literal": {
                  "Value": "57.95788880808141D"
                }
              }
            }
          },
          "selector": {
            "metadata": "Sum(ssr_history.opp_booking_amt)"
          }
        },
        {
          "properties": {
            "value": {
              "expr": {
                "Literal": {
                  "Value": "94.25422922732452D"
                }
              }
            }
          },
          "selector": {
            "metadata": "users.col.full_name"
          }
        },
        {
          "properties": {
            "value": {
              "expr": {
                "Literal": {
                  "Value": "59.099926450287704D"
                }
              }
            }
          },
          "selector": {
            "metadata": "Sum(ssr_history.step_users_tot)"
          }
        },
        {
          "properties": {
            "value": {
              "expr": {
                "Literal": {
                  "Value": "78.01531544212857D"
                }
              }
            }
          },
          "selector": {
            "metadata": "Sum(ssr_history.stkhlds_all_act_count)"
          }
        },
        {
          "properties": {
            "value": {
              "expr": {
                "Literal": {
                  "Value": "68.95902063092943D"
                }
              }
            }
          },
          "selector": {
            "metadata": "Sum(ssr_history.stkhlds_all_act_eng_count)"
          }
        },
        {
          "properties": {
            "value": {
              "expr": {
                "Literal": {
                  "Value": "81.05787782960574D"
                }
              }
            }
          },
          "selector": {
            "metadata": "ssr_history.stkhlds_secondary_contact_title_seniority"
          }
        },
        {
          "properties": {
            "value": {
              "expr": {
                "Literal": {
                  "Value": "81.17398410583037D"
                }
              }
            }
          },
          "selector": {
            "metadata": "ssr_history.step_outcome"
          }
        },
        {
          "properties": {
            "value": {
              "expr": {
                "Literal": {
                  "Value": "57.768528146720975D"
                }
              }
            }
          },
          "selector": {
            "metadata": "Sum(ssr_history.step_sequence)"
          }
        }
      ],
      "values": [
        {
          "properties": {
            "wordWrap": {
              "expr": {
                "Literal": {
                  "Value": "false"
                }
              }
            },
            "fontColorPrimary": {
              "solid": {
                "color": {
                  "expr": {
                    "Literal": {
                      "Value": "'#414355'"
                    }
                  }
                }
              }
            },
            "fontColorSecondary": {
              "solid": {
                "color": {
                  "expr": {
                    "Literal": {
                      "Value": "'#414355'"
                    }
                  }
                }
              }
            },
            "backColorSecondary": {
              "solid": {
                "color": {
                  "expr": {
                    "ThemeDataColor": {
                      "ColorId": 0,
                      "Percent": 0
                    }
                  }
                }
              }
            },
            "backColorPrimary": {
              "solid": {
                "color": {
                  "expr": {
                    "Literal": {
                      "Value": "'#F2F2F1'"
                    }
                  }
                }
              }
            },
            "outlineStyle": {
              "expr": {
                "Literal": {
                  "Value": "5D"
                }
              }
            },
            "outlineWeight": {
              "expr": {
                "Literal": {
                  "Value": "1D"
                }
              }
            }
          }
        }
      ],
      "columnHeaders": [
        {
          "properties": {
            "fontColor": {
              "solid": {
                "color": {
                  "expr": {
                    "Literal": {
                      "Value": "'#414355'"
                    }
                  }
                }
              }
            },
            "backColor": {
              "solid": {
                "color": {
                  "expr": {
                    "Literal": {
                      "Value": "'#7FD3D3'"
                    }
                  }
                }
              }
            },
            "fontFamily": {
              "expr": {
                "Literal": {
                  "Value": "'''Segoe UI'', wf_segoe-ui_normal, helvetica, arial, sans-serif'"
                }
              }
            },
            "outlineStyle": {
              "expr": {
                "Literal": {
                  "Value": "0D"
                }
              }
            }
          }
        }
      ],
      "grid": [
        {
          "properties": {
            "outlineColor": {
              "solid": {
                "color": {
                  "expr": {
                    "ThemeDataColor": {
                      "ColorId": 1,
                      "Percent": 0
                    }
                  }
                }
              }
            },
            "outlineWeight": {
              "expr": {
                "Literal": {
                  "Value": "2D"
                }
              }
            },
            "gridHorizontalColor": {
              "solid": {
                "color": {
                  "expr": {
                    "Literal": {
                      "Value": "'#414355'"
                    }
                  }
                }
              }
            },
            "gridVertical": {
              "expr": {
                "Literal": {
                  "Value": "true"
                }
              }
            },
            "gridVerticalColor": {
              "solid": {
                "color": {
                  "expr": {
                    "Literal": {
                      "Value": "'#414355'"
                    }
                  }
                }
              }
            }
          }
        }
      ],
      "columnFormatting": [
        {
          "properties": {
            "fontColor": {
              "solid": {
                "color": {
                  "expr": {
                    "Literal": {
                      "Value": "'#4A4C60'"
                    }
                  }
                }
              }
            },
            "backColor": {
              "solid": {
                "color": {
                  "expr": {
                    "Literal": {
                      "Value": "'#4A4C60'"
                    }
                  }
                }
              }
            },
            "styleValues": {
              "expr": {
                "Literal": {
                  "Value": "true"
                }
              }
            },
            "styleHeader": {
              "expr": {
                "Literal": {
                  "Value": "true"
                }
              }
            },
            "styleTotal": {
              "expr": {
                "Literal": {
                  "Value": "true"
                }
              }
            }
          },
          "selector": {
            "metadata": "ssr_history.step_id"
          }
        },
        {
          "properties": {
            "styleHeader": {
              "expr": {
                "Literal": {
                  "Value": "true"
                }
              }
            },
            "styleTotal": {
              "expr": {
                "Literal": {
                  "Value": "true"
                }
              }
            },
            "backColor": {
              "solid": {
                "color": {
                  "expr": {
                    "Literal": {
                      "Value": "'#7FD3D3'"
                    }
                  }
                }
              }
            }
          },
          "selector": {
            "metadata": "ssr_history._sys_filt_start_date"
          }
        },
        {
          "properties": {
            "styleHeader": {
              "expr": {
                "Literal": {
                  "Value": "true"
                }
              }
            },
            "styleTotal": {
              "expr": {
                "Literal": {
                  "Value": "true"
                }
              }
            },
            "backColor": {
              "solid": {
                "color": {
                  "expr": {
                    "Literal": {
                      "Value": "'#7FD3D3'"
                    }
                  }
                }
              }
            }
          },
          "selector": {
            "metadata": "ssr_history.step_name"
          }
        },
        {
          "properties": {
            "styleHeader": {
              "expr": {
                "Literal": {
                  "Value": "true"
                }
              }
            },
            "styleTotal": {
              "expr": {
                "Literal": {
                  "Value": "true"
                }
              }
            },
            "backColor": {
              "solid": {
                "color": {
                  "expr": {
                    "Literal": {
                      "Value": "'#7FD3D3'"
                    }
                  }
                }
              }
            }
          },
          "selector": {
            "metadata": "ssr_history._sys_filt_end_date"
          }
        },
        {
          "properties": {
            "backColor": {
              "solid": {
                "color": {
                  "expr": {
                    "Literal": {
                      "Value": "'#7FD3D3'"
                    }
                  }
                }
              }
            },
            "styleHeader": {
              "expr": {
                "Literal": {
                  "Value": "true"
                }
              }
            },
            "styleTotal": {
              "expr": {
                "Literal": {
                  "Value": "true"
                }
              }
            }
          },
          "selector": {
            "metadata": "ssr_history.step_outcome"
          }
        },
        {
          "properties": {
            "backColor": {
              "solid": {
                "color": {
                  "expr": {
                    "Literal": {
                      "Value": "'#7FD3D3'"
                    }
                  }
                }
              }
            },
            "styleHeader": {
              "expr": {
                "Literal": {
                  "Value": "true"
                }
              }
            },
            "styleTotal": {
              "expr": {
                "Literal": {
                  "Value": "true"
                }
              }
            }
          },
          "selector": {
            "metadata": "ssr_history.entity_qual_bucket"
          }
        },
        {
          "properties": {
            "backColor": {
              "solid": {
                "color": {
                  "expr": {
                    "Literal": {
                      "Value": "'#7FD3D3'"
                    }
                  }
                }
              }
            },
            "styleHeader": {
              "expr": {
                "Literal": {
                  "Value": "true"
                }
              }
            },
            "styleTotal": {
              "expr": {
                "Literal": {
                  "Value": "true"
                }
              }
            }
          },
          "selector": {
            "metadata": "Sum(ssr_history.step_success_prob)"
          }
        },
        {
          "properties": {
            "styleHeader": {
              "expr": {
                "Literal": {
                  "Value": "true"
                }
              }
            },
            "styleTotal": {
              "expr": {
                "Literal": {
                  "Value": "true"
                }
              }
            },
            "backColor": {
              "solid": {
                "color": {
                  "expr": {
                    "Literal": {
                      "Value": "'#7FD3D3'"
                    }
                  }
                }
              }
            }
          },
          "selector": {
            "metadata": "Sum(ssr_history.opp_booking_amt)"
          }
        },
        {
          "properties": {
            "styleHeader": {
              "expr": {
                "Literal": {
                  "Value": "true"
                }
              }
            },
            "styleTotal": {
              "expr": {
                "Literal": {
                  "Value": "true"
                }
              }
            },
            "backColor": {
              "solid": {
                "color": {
                  "expr": {
                    "Literal": {
                      "Value": "'#7FD3D3'"
                    }
                  }
                }
              }
            }
          },
          "selector": {
            "metadata": "ssr_history.opp_final_stage"
          }
        },
        {
          "properties": {
            "backColor": {
              "solid": {
                "color": {
                  "expr": {
                    "Literal": {
                      "Value": "'#7FD3D3'"
                    }
                  }
                }
              }
            },
            "styleTotal": {
              "expr": {
                "Literal": {
                  "Value": "true"
                }
              }
            },
            "styleHeader": {
              "expr": {
                "Literal": {
                  "Value": "true"
                }
              }
            }
          },
          "selector": {
            "metadata": "Sum(ssr_history.step_length_in_days)"
          }
        },
        {
          "properties": {
            "backColor": {
              "solid": {
                "color": {
                  "expr": {
                    "Literal": {
                      "Value": "'#7FD3D3'"
                    }
                  }
                }
              }
            },
            "styleTotal": {
              "expr": {
                "Literal": {
                  "Value": "true"
                }
              }
            },
            "styleHeader": {
              "expr": {
                "Literal": {
                  "Value": "true"
                }
              }
            }
          },
          "selector": {
            "metadata": "users.col.full_name"
          }
        },
        {
          "properties": {
            "backColor": {
              "solid": {
                "color": {
                  "expr": {
                    "Literal": {
                      "Value": "'#7FD3D3'"
                    }
                  }
                }
              }
            },
            "styleTotal": {
              "expr": {
                "Literal": {
                  "Value": "true"
                }
              }
            },
            "styleHeader": {
              "expr": {
                "Literal": {
                  "Value": "true"
                }
              }
            }
          },
          "selector": {
            "metadata": "ssr_history.step_owner_user_role"
          }
        },
        {
          "properties": {
            "backColor": {
              "solid": {
                "color": {
                  "expr": {
                    "Literal": {
                      "Value": "'#7FD3D3'"
                    }
                  }
                }
              }
            },
            "styleTotal": {
              "expr": {
                "Literal": {
                  "Value": "true"
                }
              }
            },
            "styleHeader": {
              "expr": {
                "Literal": {
                  "Value": "true"
                }
              }
            }
          },
          "selector": {
            "metadata": "Sum(ssr_history.step_users_tot)"
          }
        },
        {
          "properties": {
            "backColor": {
              "solid": {
                "color": {
                  "expr": {
                    "Literal": {
                      "Value": "'#7FD3D3'"
                    }
                  }
                }
              }
            },
            "styleTotal": {
              "expr": {
                "Literal": {
                  "Value": "true"
                }
              }
            },
            "styleHeader": {
              "expr": {
                "Literal": {
                  "Value": "true"
                }
              }
            }
          },
          "selector": {
            "metadata": "Sum(ssr_history.stkhlds_all_act_count)"
          }
        },
        {
          "properties": {
            "backColor": {
              "solid": {
                "color": {
                  "expr": {
                    "Literal": {
                      "Value": "'#7FD3D3'"
                    }
                  }
                }
              }
            },
            "styleHeader": {
              "expr": {
                "Literal": {
                  "Value": "true"
                }
              }
            },
            "styleTotal": {
              "expr": {
                "Literal": {
                  "Value": "true"
                }
              }
            }
          },
          "selector": {
            "metadata": "Sum(ssr_history.stkhlds_all_act_eng_count)"
          }
        },
        {
          "properties": {
            "styleTotal": {
              "expr": {
                "Literal": {
                  "Value": "true"
                }
              }
            },
            "styleHeader": {
              "expr": {
                "Literal": {
                  "Value": "true"
                }
              }
            },
            "backColor": {
              "solid": {
                "color": {
                  "expr": {
                    "Literal": {
                      "Value": "'#7FD3D3'"
                    }
                  }
                }
              }
            }
          },
          "selector": {
            "metadata": "ssr_history.stkhlds_secondary_contact_title_seniority"
          }
        }
      ]
    },
    "visualContainerObjects": {
      "background": [
        {
          "properties": {
            "show": {
              "expr": {
                "Literal": {
                  "Value": "false"
                }
              }
            }
          }
        }
      ]
    },
    "drillFilterOtherVisuals": true
  }
}