{
  "$schema": "https://developer.microsoft.com/json-schemas/fabric/item/report/definition/visualContainer/2.2.0/schema.json",
  "name": "55bf2cd224c28c3f8fc7",
  "position": {
    "x": 2861.2565445026175,
    "y": 2440.6851897066917,
    "z": 33000,
    "height": 49.738219895287955,
    "width": 112.56544502617801,
    "tabOrder": 33000
  },
  "visual": {
    "visualType": "textbox",
    "objects": {
      "general": [
        {
          "properties": {
            "paragraphs": [
              {
                "textRuns": [
                  {
                    "value": "Release Notes",
                    "textStyle": {
                      "textDecoration": "underline",
                      "color": "#faa200"
                    },
                    "url": "https://github.com/cienai/IntegrationHub/releases"
                  }
                ]
              }
            ]
          }
        }
      ]
    },
    "visualContainerObjects": {
      "background": [
        {
          "properties": {
            "show": {
              "expr": {
                "Literal": {
                  "Value": "false"
                }
              }
            }
          }
        }
      ]
    },
    "drillFilterOtherVisuals": true
  }
}