{
  "$schema": "https://developer.microsoft.com/json-schemas/fabric/item/report/definition/visualContainer/2.4.0/schema.json",
  "name": "dcaf5bbf423dd02c5053",
  "position": {
    "x": 54.799115883306442,
    "y": 1499.8816565002887,
    "z": 57000,
    "height": 199.12574238973278,
    "width": 332.42479308038037,
    "tabOrder": 56000
  },
  "visual": {
    "visualType": "lineChart",
    "query": {
      "queryState": {
        "Category": {
          "projections": [
            {
              "field": {
                "HierarchyLevel": {
                  "Expression": {
                    "Hierarchy": {
                      "Expression": {
                        "PropertyVariationSource": {
                          "Expression": {
                            "SourceRef": {
                              "Entity": "cal_end_dates"
                            }
                          },
                          "Name": "Variación",
                          "Property": "Date"
                        }
                      },
                      "Hierarchy": "Date Hierarchy"
                    }
                  },
                  "Level": "Quarter"
                }
              },
              "queryRef": "cal_end_dates.Date.Variación.Date Hierarchy.Quarter",
              "nativeQueryRef": "Date Quarter1",
              "active": true
            }
          ]
        },
        "Y": {
          "projections": [
            {
              "field": {
                "Measure": {
                  "Expression": {
                    "SourceRef": {
                      "Entity": "metadata_heatmap_items"
                    }
                  },
                  "Property": "meas.getKPI1_score_cy_5q"
                }
              },
              "queryRef": "heatmap.meas.getKPI1_score_cy_5q",
              "nativeQueryRef": "meas.getKPI1_score_cy_5q"
            }
          ]
        }
      }
    },
    "objects": {
      "categoryAxis": [
        {
          "properties": {
            "labelColor": {
              "solid": {
                "color": {
                  "expr": {
                    "Literal": {
                      "Value": "'#E9EEDA'"
                    }
                  }
                }
              }
            },
            "showAxisTitle": {
              "expr": {
                "Literal": {
                  "Value": "false"
                }
              }
            }
          }
        }
      ],
      "valueAxis": [
        {
          "properties": {
            "labelColor": {
              "solid": {
                "color": {
                  "expr": {
                    "Literal": {
                      "Value": "'#E9EEDA'"
                    }
                  }
                }
              }
            },
            "gridlineColor": {
              "solid": {
                "color": {
                  "expr": {
                    "Literal": {
                      "Value": "'#E9EEDA'"
                    }
                  }
                }
              }
            },
            "showAxisTitle": {
              "expr": {
                "Literal": {
                  "Value": "false"
                }
              }
            },
            "end": {
              "expr": {
                "Literal": {
                  "Value": "100D"
                }
              }
            },
            "start": {
              "expr": {
                "Literal": {
                  "Value": "0D"
                }
              }
            }
          }
        }
      ],
      "lineStyles": [
        {
          "properties": {
            "showMarker": {
              "expr": {
                "Literal": {
                  "Value": "false"
                }
              }
            }
          }
        }
      ]
    },
    "visualContainerObjects": {
      "title": [
        {
          "properties": {
            "text": {
              "expr": {
                "Literal": {
                  "Value": "'How is the KPI 1 Score Trending? ⁷'"
                }
              }
            },
            "fontFamily": {
              "expr": {
                "Literal": {
                  "Value": "'''Segoe UI Bold'', wf_segoe-ui_bold, helvetica, arial, sans-serif'"
                }
              }
            },
            "fontSize": {
              "expr": {
                "Literal": {
                  "Value": "14D"
                }
              }
            },
            "fontColor": {
              "solid": {
                "color": {
                  "expr": {
                    "Literal": {
                      "Value": "'#E9EEDA'"
                    }
                  }
                }
              }
            },
            "show": {
              "expr": {
                "Literal": {
                  "Value": "true"
                }
              }
            },
            "underline": {
              "expr": {
                "Literal": {
                  "Value": "true"
                }
              }
            }
          }
        }
      ],
      "background": [
        {
          "properties": {
            "show": {
              "expr": {
                "Literal": {
                  "Value": "false"
                }
              }
            }
          }
        }
      ],
      "subTitle": [
        {
          "properties": {
            "show": {
              "expr": {
                "Literal": {
                  "Value": "false"
                }
              }
            },
            "text": {
              "expr": {
                "Literal": {
                  "Value": "'KPI Value Trend'"
                }
              }
            },
            "fontSize": {
              "expr": {
                "Literal": {
                  "Value": "12D"
                }
              }
            },
            "fontColor": {
              "solid": {
                "color": {
                  "expr": {
                    "Literal": {
                      "Value": "'#E9EEDA'"
                    }
                  }
                }
              }
            }
          }
        }
      ]
    },
    "drillFilterOtherVisuals": true
  },
  "filterConfig": {
    "filters": [
      {
        "name": "b261860025990043682a",
        "field": {
          "HierarchyLevel": {
            "Expression": {
              "Hierarchy": {
                "Expression": {
                  "PropertyVariationSource": {
                    "Expression": {
                      "SourceRef": {
                        "Entity": "cal_end_dates"
                      }
                    },
                    "Name": "Variation",
                    "Property": "Date"
                  }
                },
                "Hierarchy": "Date Hierarchy"
              }
            },
            "Level": "Quarter"
          }
        },
        "type": "Categorical",
        "filter": {
          "Version": 2,
          "From": [
            {
              "Name": "l",
              "Entity": "LocalDateTable_d9cd643e-7eb2-4078-b7d4-6261fea9cd66",
              "Type": 0
            }
          ],
          "Where": [
            {
              "Condition": {
                "Not": {
                  "Expression": {
                    "In": {
                      "Expressions": [
                        {
                          "Column": {
                            "Expression": {
                              "SourceRef": {
                                "Source": "l"
                              }
                            },
                            "Property": "Quarter"
                          }
                        }
                      ],
                      "Values": [
                        [
                          {
                            "Literal": {
                              "Value": "null"
                            }
                          }
                        ]
                      ]
                    }
                  }
                }
              },
              "Annotations": {
                "filterExpressionMetadata": {
                  "expressions": [
                    {
                      "HierarchyLevel": {
                        "Expression": {
                          "Hierarchy": {
                            "Expression": {
                              "PropertyVariationSource": {
                                "Expression": {
                                  "SourceRef": {
                                    "Entity": "cal_end_dates"
                                  }
                                },
                                "Name": "Variation",
                                "Property": "Date"
                              }
                            },
                            "Hierarchy": "Date Hierarchy"
                          }
                        },
                        "Level": "Quarter"
                      }
                    }
                  ],
                  "decomposedIdentities": {
                    "values": [
                      [
                        {
                          "0": [
                            {
                              "Literal": {
                                "Value": "null"
                              }
                            }
                          ]
                        }
                      ]
                    ],
                    "columns": [
                      {
                        "value": {
                          "Column": {
                            "Expression": {
                              "SourceRef": {
                                "Entity": "LocalDateTable_d9cd643e-7eb2-4078-b7d4-6261fea9cd66"
                              }
                            },
                            "Property": "Quarter"
                          }
                        }
                      }
                    ]
                  },
                  "valueMap": [
                    {
                      "0": "(Blank)"
                    }
                  ]
                }
              }
            }
          ]
        },
        "howCreated": "User",
        "objects": {
          "general": [
            {
              "properties": {
                "isInvertedSelectionMode": {
                  "expr": {
                    "Literal": {
                      "Value": "true"
                    }
                  }
                }
              }
            }
          ]
        }
      }
    ]
  }
}